Metadata-Version: 2.0
Name: aioagi
Version: 1.2.0
Summary: Async agi client/server framework (asyncio)
Home-page: https://gitlab.com/VadimShakurov/aioagi.git
Author: Shakurov Vadim Vladimirovich
Author-email: apelsinsd@gmail.com
License: Apache 2
Keywords: aiogi asyncio asterisk telephony voip
Platform: UNKNOWN
Classifier: License :: OSI Approved :: Apache Software License
Classifier: Intended Audience :: Developers
Classifier: Programming Language :: Python
Classifier: Programming Language :: Python :: 3.6
Classifier: Programming Language :: Python :: 3.7
Classifier: Programming Language :: Python :: 3.8
Classifier: Operating System :: POSIX
Classifier: Operating System :: MacOS :: MacOS X
Classifier: Operating System :: Microsoft :: Windows
Classifier: Topic :: Communications :: Internet Phone
Classifier: Topic :: Communications :: Telephony
Classifier: Topic :: Software Development :: Libraries :: Python Modules
Classifier: Framework :: AsyncIO
Provides-Extra: dev
Provides-Extra: testing
Requires-Dist: aiohttp (<3.5.0,>=3.4.0)
Provides-Extra: dev
Requires-Dist: ipdb; extra == 'dev'
Requires-Dist: ipython; extra == 'dev'
Provides-Extra: testing
Requires-Dist: coverage; extra == 'testing'
Requires-Dist: pytest; extra == 'testing'
Requires-Dist: pytest-asyncio; extra == 'testing'
Requires-Dist: async-generator; extra == 'testing'
Requires-Dist: pytest-sugar; extra == 'testing'
Requires-Dist: pytest-cov; extra == 'testing'
